pypkjs/__init__.py
pypkjs/__main__.py
pypkjs/version.py
pypkjs/javascript/__init__.py
pypkjs/javascript/console.py
pypkjs/javascript/events.py
pypkjs/javascript/exceptions.py
pypkjs/javascript/localstorage.py
pypkjs/javascript/pebble.py
pypkjs/javascript/performance.py
pypkjs/javascript/runtime.py
pypkjs/javascript/safe_requests.py
pypkjs/javascript/timers.py
pypkjs/javascript/ws.py
pypkjs/javascript/xhr.py
pypkjs/javascript/navigator/GeoLiteCity.dat
pypkjs/javascript/navigator/__init__.py
pypkjs/javascript/navigator/geolocation.py
pypkjs/runner/__init__.py
pypkjs/runner/pebble_manager.py
pypkjs/runner/terminal.py
pypkjs/runner/websocket.py
pypkjs/timeline/__init__.py
pypkjs/timeline/actions.py
pypkjs/timeline/attributes.py
pypkjs/timeline/colours.py
pypkjs/timeline/layouts.json
pypkjs/timeline/model.py
pypkjs/timeline/urls.py
pypkjs/timeline/websync.py
pypkjs-2.0.6.dist-info/licenses/LICENSE
pypkjs-2.0.6.dist-info/METADATA
pypkjs-2.0.6.dist-info/WHEEL
pypkjs-2.0.6.dist-info/entry_points.txt
pypkjs-2.0.6.dist-info/top_level.txt
pypkjs-2.0.6.dist-info/RECORD
