Metadata-Version: 2.4
Name: pypkjs
Version: 2.0.6
Summary: A Pebble phone app simulator written in Python
Home-page: https://github.com/coredevices/pypkjs
Author: Core Devices LLC
Author-email: griffin@griffinli.com
License: MIT
License-File: LICENSE
Requires-Dist: gevent>=24.11.1
Requires-Dist: gevent-websocket>=0.10.1
Requires-Dist: greenlet>=3.2.3
Requires-Dist: peewee>=3.17.9
Requires-Dist: pygeoip>=0.3.2
Requires-Dist: pypng>=0.20220715.0
Requires-Dist: python-dateutil>=2.4.1
Requires-Dist: requests>=2.32.3
Requires-Dist: sh>=2.2.1
Requires-Dist: six>=1.17.0
Requires-Dist: websocket-client>=1.8.0
Requires-Dist: libpebble2>=0.0.27
Requires-Dist: netaddr>=0.7.18
Requires-Dist: stpyv8>=13.1.201.22
Dynamic: author
Dynamic: author-email
Dynamic: home-page
Dynamic: license
Dynamic: license-file
Dynamic: requires-dist
Dynamic: summary
